headlamp-0.1.57.dist-info/RECORD
headlamp-0.1.57.dist-info/WHEEL
headlamp-0.1.57.dist-info/entry_points.txt
headlamp-0.1.57.dist-info/top_level.txt
headlamp-0.1.57.dist-info/METADATA
headlamp/_cli.py
headlamp/__init__.py
headlamp/_bin.py
headlamp/bin/headlamp
