Metadata-Version: 2.4
Name: headlamp
Version: 0.1.57
Summary: Dependency-graph based test runner in Rust that supports Rust, Python, and JavaScript.
Author: David Piper
License: MIT
Project-URL: Homepage, https://github.com/dbpiper/headlamp
Project-URL: Repository, https://github.com/dbpiper/headlamp
Keywords: testing,cli,pytest,jest,nextest
Classifier: Programming Language :: Python :: 3
Classifier: Programming Language :: Python :: 3 :: Only
Requires-Python: >=3.8
